[
    {
        "subreddit": "AskReddit",
        "id": "wkx1su",
        "time": "1660173620",
        "background_credit": "bbswitzer",
        "reddit_title": "Whats a commercial youll never forget",
        "filename": "What's a commercial you'll never forget.mp4"
    },
    {
        "subreddit": "AskReddit",
        "id": "wl0s0j",
        "time": "1660174475",
        "background_credit": "bbswitzer",
        "reddit_title": "Whos a celebrity no one can hate",
        "filename": "Whos a celebrity no one can hate.mp4"
    },
    {
        "subreddit": "AskReddit",
        "id": "wkz9ye",
        "time": "1660175272",
        "background_credit": "bbswitzer",
        "reddit_title": "Whats a sport no matter the skill level that you dont find impressive at all",
        "filename": "Whats a sport no matter the skill level that you dont find impressive at all.mp4"
    },
    {
        "subreddit": "Seattle",
        "id": "wl71ed",
        "time": "1660175918",
        "background_credit": "bbswitzer",
        "reddit_title": "Fauci gracing us with his presence at the mariners game",
        "filename": "Fauci gracing us with his presence at the mariners game.mp4"
    },
    {
        "subreddit": "BellevueWA",
        "id": "wjqyj1",
        "time": "1660176740",
        "background_credit": "bbswitzer",
        "reddit_title": "Affordable eatery in bellevue 15 a meal",
        "filename": "Affordable eatery in bellevue 15 a meal.mp4"
    },
    {
        "subreddit": "AskReddit",
        "id": "wkw7vg",
        "time": "1660177393",
        "background_credit": "bbswitzer",
        "reddit_title": "Whats something Redditors like to blindly hate",
        "filename": "Whats something Redditors like to blindly hate.mp4"
    },
    {
        "subreddit": "AskReddit",
        "id": "wl3thl",
        "time": "1660178279",
        "background_credit": "bbswitzer",
        "reddit_title": "When is the first time you remember feeling like an adult",
        "filename": "When is the first time you remember feeling like an adult.mp4"
    },
    {
        "subreddit": "AskReddit",
        "id": "wkxr4o",
        "time": "1660180365",
        "background_credit": "bbswitzer",
        "reddit_title": "What is the weirdest conspiracy theory you ever heard",
        "filename": "What is the weirdest conspiracy theory you ever heard.mp4"
    },
    {
        "subreddit": "AskReddit",
        "id": "wlaalv",
        "time": "1660181485",
        "background_credit": "bbswitzer",
        "reddit_title": "What is something you absolutely cannot fall asleep without",
        "filename": "What is something you absolutely cannot fall asleep without.mp4"
    },
    {
        "subreddit": "AskReddit",
        "id": "wlr2od",
        "time": "1660253821",
        "background_credit": "bbswitzer",
        "reddit_title": "people of reddit who survive on less than 8 hours of sleep how",
        "filename": "people of reddit who survive on less than 8 hours of sleep how.mp4"
    },
    {
        "subreddit": "AskReddit",
        "id": "wlshrl",
        "time": "1660257010",
        "background_credit": "bbswitzer",
        "reddit_title": "What would your 15 year old self think about the life you are living now",
        "filename": "What would your 15 year old self think about the life you are living now.mp4"
    },
    {
        "subreddit": "AskReddit",
        "id": "wlxu7d",
        "time": "1660289589",
        "background_credit": "bbswitzer",
        "reddit_title": "You have 24 hrs with no internet or mobile phone access what do you do to pass the time",
        "filename": "You have 24 hrs with no internet or mobile phone access what do you do to pass the time.mp4"
    },
    {
        "subreddit": "AskReddit",
        "id": "wmg8e5",
        "time": "1660338365",
        "background_credit": "bbswitzer",
        "reddit_title": "Whos an internet famous person that needs to go away",
        "filename": "Whos an internet famous person that needs to go away.mp4"
    },
    {
        "subreddit": "AskReddit",
        "id": "wmfbmp",
        "time": "1660348654",
        "background_credit": "bbswitzer",
        "reddit_title": "Guys imagine that you are the last male person on earth women will still remain what will you do",
        "filename": "Guys imagine that you are the last male person on earth women will still remain what will you do.mp4"
    },
    {
        "subreddit": "AskReddit",
        "id": "wn3rlr",
        "time": "1660422683",
        "background_credit": "bbswitzer",
        "reddit_title": "Americans what do you think is the weirdest thing about Europe",
        "filename": "Americans what do you think is the weirdest thing about Europe.mp4"
    }
]